setup.py
Flask_Twisted.egg-info/PKG-INFO
Flask_Twisted.egg-info/SOURCES.txt
Flask_Twisted.egg-info/dependency_links.txt
Flask_Twisted.egg-info/not-zip-safe
Flask_Twisted.egg-info/requires.txt
Flask_Twisted.egg-info/top_level.txt
flask_twisted/__init__.py
flask_twisted/decorators.py
flask_twisted/resource.py